construct_extensions/__init__.py
construct_extensions/_version.py
construct_extensions/alignment.py
construct_extensions/dict.py
construct_extensions/enum.py
construct_extensions/function_complex.py
construct_extensions/json.py
construct_extensions/misc.py
construct_extensions/strings.py
construct_extensions/version.py
construct_extensions-0.1.0.dist-info/licenses/LICENSE
construct_extensions-0.1.0.dist-info/METADATA
construct_extensions-0.1.0.dist-info/WHEEL
construct_extensions-0.1.0.dist-info/top_level.txt
construct_extensions-0.1.0.dist-info/RECORD
